{
  "locale": "id",
  "genres": {
    "1": "aksi",
    "2": "untuk orang dewasa",
    "3": "petualangan",
    "4": "animasi",
    "5": "anime",
    "6": "biografi",
    "7": "upacara",
    "8": "komedi",
    "9": "konser",
    "10": "kejahatan",
    "11": "dokumenter",
    "12": "drama",
    "13": "keluarga",
    "14": "fantasi",
    "15": "film noir",
    "16": "permainan",
    "17": "sejarah",
    "18": "kengerian",
    "19": "anak-anak",
    "20": "musik",
    "21": "musikal",
    "22": "misteri",
    "23": "berita",
    "24": "politik",
    "25": "realitas",
    "26": "percintaan",
    "27": "cerita fiksi",
    "28": "film pendek",
    "29": "sabun",
    "30": "olahraga",
    "31": "bicara",
    "32": "cerita seru",
    "33": "film tv",
    "34": "kejahatan",
    "35": "barat"
  }
}